COPYING.txt
MANIFEST.in
README.txt
setup.cfg
setup.py
setup_sample_unix.cfg
setup_sample_win.cfg
docs/CHANGELOG.txt
src/pymatlab/matlab.c
src/pymatlab/__init__.py
src/pymatlab/matlab.c
src/pymatlab.egg-info/PKG-INFO
src/pymatlab.egg-info/SOURCES.txt
src/pymatlab.egg-info/dependency_links.txt
src/pymatlab.egg-info/not-zip-safe
src/pymatlab.egg-info/requires.txt
src/pymatlab.egg-info/top_level.txt
src/tests/__init__.py
src/tests/alltests.py
src/tests/test_matlab.py