Metadata-Version: 1.0
Name: pymatlab
Version: 0.1.3
Summary: A python interface to MATLAB
Home-page: http://pymatlab.sourceforge.net/
Author: Joakim Moller
Author-email: joakim.moller@chalmers.se
License: UNKNOWN
Platform: UNKNOWN
Classifier: Development Status :: 3 - Alpha
Classifier: Intended Audience :: End Users/Desktop
Classifier: Intended Audience :: Developers
Classifier: Intended Audience :: Science/Research
Classifier: License :: OSI Approved :: GNU General Public License (GPL)
Classifier: Operating System :: POSIX
Classifier: Programming Language :: C
Classifier: Programming Language :: Python
